LICENSE.rst
MANIFEST.in
README.rst
setup.py
django_statsd/__init__.py
django_statsd/celery.py
django_statsd/middleware.py
django_statsd/models.py
django_statsd/panel.py
django_statsd/plugins.py
django_statsd/test_settings.py
django_statsd/tests.py
django_statsd/urls.py
django_statsd/views.py
django_statsd/clients/__init__.py
django_statsd/clients/log.py
django_statsd/clients/moz_metlog.py
django_statsd/clients/normal.py
django_statsd/clients/nose.py
django_statsd/clients/null.py
django_statsd/clients/toolbar.py
django_statsd/loggers/__init__.py
django_statsd/loggers/errors.py
django_statsd/management/__init__.py
django_statsd/management/commands/__init__.py
django_statsd/management/commands/statsd_ping.py
django_statsd/patches/__init__.py
django_statsd/patches/cache.py
django_statsd/patches/db.py
django_statsd/patches/utils.py
django_statsd/static/stick.js
django_statsd/templates/toolbar_statsd/statsd.html
django_statsd_mozilla.egg-info/PKG-INFO
django_statsd_mozilla.egg-info/SOURCES.txt
django_statsd_mozilla.egg-info/dependency_links.txt
django_statsd_mozilla.egg-info/entry_points.txt
django_statsd_mozilla.egg-info/not-zip-safe
django_statsd_mozilla.egg-info/pbr.json
django_statsd_mozilla.egg-info/requires.txt
django_statsd_mozilla.egg-info/top_level.txt