Metadata-Version: 1.1
Name: django-statsd-mozilla
Version: 0.3.16
Summary: Django interface with statsd
Home-page: https://github.com/andymckay/django-statsd
Author: Andy McKay
Author-email: andym@mozilla.com
License: BSD
Platform: UNKNOWN
Classifier: Intended Audience :: Developers
Classifier: Natural Language :: English
Classifier: Operating System :: OS Independent
Classifier: Framework :: Django
